{
    "fluentMethods": true,
    "relationships": [
        {
            "relationshipType": "many-to-one",
            "relationshipName": "bill",
            "otherEntityName": "bill",
            "otherEntityField": "id"
        }
    ],
    "fields": [
        {
            "fieldName": "description",
            "fieldType": "Integer",
            "fieldValidateRules": [
                "required"
            ]
        }
    ],
    "changelogDate": "20180516141346",
    "entityTableName": "room_service",
    "dto": "no",
    "pagination": "no",
    "service": "serviceImpl",
    "jpaMetamodelFiltering": false,
    "angularJSSuffix": "config"
}